<?xml version="1.0" encoding="utf-8" ?><dwsync><file name="_facebook-feed.scss" server="107.180.47.66" local="3639931186" remote="3639979380" Dst="-1" /><file name="_activities.scss" server="107.180.47.66" local="3639557962" remote="3639979380" Dst="-1" /><file name="_email-form.scss" server="107.180.47.66" local="3639994276" remote="3639979920" Dst="-1" /><file name="_general.scss" server="107.180.47.66" local="3639561855" remote="3639979380" Dst="-1" /><file name="_google-map.scss" server="107.180.47.66" local="3639553472" remote="3639979380" Dst="-1" /><file name="_footer.scss" server="107.180.47.66" local="3640072801" remote="3640857180" Dst="-1" /><file name="_main-header.scss" server="107.180.47.66" local="3639684447" remote="3639979380" Dst="-1" /><file name="_image-gallery.scss" server="107.180.47.66" local="3640072503" remote="3640058280" Dst="-1" /><file name="_index.scss" server="107.180.47.66" local="3639576961" remote="3639979380" Dst="-1" /><file name="_modal.scss" server="107.180.47.66" local="3640072449" remote="3640058280" Dst="-1" /><file name="_main-nav.scss" server="107.180.47.66" local="3639930349" remote="3639979380" Dst="-1" /><file name="_mobile-nav.scss" server="107.180.47.66" local="3639588319" remote="3639979380" Dst="-1" /><file name="_reviews.scss" server="107.180.47.66" local="3639824793" remote="3639979380" Dst="-1" /><file name="_services.scss" server="107.180.47.66" local="3639826813" remote="3639979380" Dst="-1" /><file name="_typography.scss" server="107.180.47.66" local="3639931785" remote="3639979380" Dst="-1" /></dwsync>